<?xml version="1.0" encoding="ISO-8859-1"?>
<!DOCTYPE queries [
<!ELEMENT queries (query*)>
<!ELEMENT query (use-case+, description,paginacao?,command+, projecao?, ordenacoes?)>
<!ELEMENT use-case    (#PCDATA) >
<!ELEMENT description (#PCDATA) >
<!ELEMENT command     (#PCDATA) >
<!ELEMENT parametros  (#PCDATA) >
<!ELEMENT projecao (#PCDATA) >
<!ELEMENT paginar  (#PCDATA) >
<!ELEMENT paginacao (#PCDATA) >
<!ELEMENT colunaCodigo    (#PCDATA) >
<!ELEMENT colunaDescricao    (#PCDATA) >
<!ELEMENT numeroOcorrenciasPorPagina    (#PCDATA) >
<!ELEMENT primeiraCondicao    (#PCDATA) >
<!ELEMENT ascendente    (#PCDATA) >
<!ELEMENT ordenacoes (ordenacao+)>
<!ELEMENT ordenacao (#PCDATA)>
<!ELEMENT sql  (#PCDATA) >
<!ATTLIST ordenacao chave CDATA    #REQUIRED >
<!ATTLIST ordenacao default CDATA    #IMPLIED >
<!ATTLIST command parametros CDATA    #IMPLIED  >
<!ATTLIST command paginar CDATA    #IMPLIED  >
<!ATTLIST use-case name CDATA    #REQUIRED >
<!ATTLIST query name CDATA    #REQUIRED >
<!ATTLIST paginacao colunaCodigo CDATA    #REQUIRED>
<!ATTLIST paginacao colunaDescricao CDATA    #REQUIRED>
<!ATTLIST paginacao numeroOcorrenciasPorPagina CDATA    #REQUIRED>
<!ATTLIST paginacao primeiraCondicao CDATA    #REQUIRED>
<!ATTLIST paginacao ascendente CDATA    #REQUIRED>
<!ATTLIST paginacao hint CDATA    #REQUIRED>
<!ATTLIST paginacao hintAuxiliar CDATA   #IMPLIED >
]>
<queries>

	<query name="OBTER_CANAL_DDA">
		<use-case name="OBTER_CANAL_DDA"></use-case>
		<description>Obtém o canal DDA pelo canal CTR</description>
		<command>
				<![CDATA[
					SELECT c.codCanalPagamento
					FROM CanalPagamentoDDACTR c 
					WHERE c.idCanal = <bancoob:valorOql valor="${canalCTR}"/>
				]]>
		</command>
	</query>

</queries>
